otel_log_proto_mapper/__init__.py
otel_log_proto_mapper/converter.py
otel_log_proto_mapper-0.1.5.dist-info/licenses/LICENSE
tests/test_converter.py
otel_log_proto_mapper-0.1.5.dist-info/METADATA
otel_log_proto_mapper-0.1.5.dist-info/WHEEL
otel_log_proto_mapper-0.1.5.dist-info/top_level.txt
otel_log_proto_mapper-0.1.5.dist-info/RECORD
