Metadata-Version: 2.4
Name: otel-log-proto-mapper
Version: 0.1.5
Summary: A Python library to map standard logging.LogRecord messages to OpenTelemetry OTLP Log Protobufs.
Author-email: Andrey Ilyin <jemmix@gmail.com>
License-Expression: MIT
Project-URL: Homepage, https://github.com/jemmix/otel-log-proto-mapper
Project-URL: Bug Tracker, https://github.com/jemmix/otel-log-proto-mapper/issues
Keywords: opentelemetry,logging,otel,protobuf,logs,mapper
Classifier: Programming Language :: Python :: 3
Classifier: Operating System :: OS Independent
Classifier: Topic :: System :: Logging
Classifier: Framework :: OpenTelemetry
Requires-Python: >=3.9
License-File: LICENSE
Requires-Dist: opentelemetry-proto>=1.34.1
Dynamic: license-file
